<?xml version="1.0" encoding="utf-8"?>
<includes>
    <include name="LandscapeThumbs">
        <control type="image">
            <posx>-3</posx>
            <posy>67</posy>
            <width>500</width>
            <height>287</height>
            <aspectratio scalediffuse="false">scale</aspectratio>
            <texture background="true" diffuse="thumbs/multiplex_tvmask.png" fallback="DefaultTVShows.png">$VAR[LandscapeThumbVar]</texture>
            <bordersize>9</bordersize>
        </control>
        <control type="image">
            <posx>-3</posx>
            <posy>97</posy>
            <width>500</width>
            <height>147</height>
            <aspectratio>keep</aspectratio>
            <texture background="true">$INFO[ListItem.Art(clearlogo)]</texture>
            <visible>Container.Content(movies) + IsEmpty(ListItem.Art(landscape))</visible>
        </control>
        <control type="image">
            <posx>-3</posx>
            <posy>338</posy>
            <width>500</width>
            <height>247</height>
            <aspectratio scalediffuse="false">scale</aspectratio>
            <texture flipy="true" background="true" diffuse="thumbs/multiplex_tvmaskreflect.png" fallback="DefaultTVShows.png">$VAR[LandscapeThumbVar]</texture>
            <bordersize>9</bordersize>
            <animation effect="fade" start="100" end="40" time="200">Focus</animation>
            <animation effect="fade" start="40" end="100" time="200">UnFocus</animation>
        </control>
        <control type="image">
            <posx>-3</posx>
            <posy>67</posy>
            <width>500</width>
            <height>287</height>
            <aspectratio scalediffuse="false">scale</aspectratio>
            <texture diffuse="thumbs/multiplex_tvmask.png">thumbs/multiplex_tv_glass_reflect.png</texture>
            <bordertexture border="9">thumbs/multiplex_tvborder.png</bordertexture>
            <bordersize>9</bordersize>
        </control>
        <control type="group">
            <visible>Container.Content(episodes) + !IsEmpty(ListItem.Title) + !Skin.HasSetting(disableepno)</visible>
            <control type="image">
                <posx>140</posx>
                <posy>326</posy>
                <width>218</width>
                <height>70</height>
                <aspectratio scalediffuse="false">keep</aspectratio>
                <texture>thumbs/multiplex_labelblock.png</texture>
            </control>
            <control type="label">
                <posx>249</posx>
                <posy>300</posy>
                <width>375</width>
                <height>90</height>
                <align>center</align>
                <font>Font_Reg15_Caps</font>
                <label>$INFO[ListItem.Episode,$LOCALIZE[20359] ]</label>
            </control>
        </control>
        <control type="image">
            <posx>399</posx>
            <posy>75</posy>
            <width>90</width>
            <height>90</height>
            <include>OverlayVisibility0</include>
            <visible>![[Skin.HasSetting(landscapelogo) | Skin.HasSetting(landscapeonelogo)] + [Container.Content(tvshows) | Container.Content(movies)]]</visible>
        </control>
        <control type="group">
            <posx>-20</posx>
            <posy>50</posy>
            <include>UnwatchedIcon</include>
        </control>
    </include>
    <include name="contents503list">
        <posx>-330</posx>
        <posy>612</posy>
        <width>2580</width>
        <height>600</height>
        <onleft>503</onleft>
        <onright>503</onright>
        <onup>7000</onup>
        <ondown condition="![Skin.HasSetting(landscapeonelogo) + [Container.Content(tvshows) | Container.Content(movies)]]">61</ondown>
        <ondown condition="[Skin.HasSetting(landscapeonelogo) + [Container.Content(tvshows) | Container.Content(movies)]] + !IsEmpty(ListItem.Trailer)">9000</ondown>
        <ondown condition="[Skin.HasSetting(landscapeonelogo) + [Container.Content(tvshows) | Container.Content(movies)]] + IsEmpty(ListItem.Trailer)">7000</ondown>
        <orientation>horizontal</orientation>
        <viewtype label="$LOCALIZE[31150]">BigWrap</viewtype>
        <pagecontrol>61</pagecontrol>
        <scrolltime tween="quadratic">300</scrolltime>
        <focusposition>2</focusposition>
        <preloaditems>2</preloaditems>
        <visible>[Container.Content(TVShows) | Container.Content(Seasons) | Container.Content(Episodes) | Container.Content(Movies) | Container.Content(artists)]</visible>
        <include>Animation_OpenCloseZoom_New</include>
        <animation effect="slide" end="52" time="400" tween="cubic" easing="inout" condition="[Skin.HasSetting(landscapelogo) | Skin.HasSetting(landscapeclearart)] + [Container.Content(tvshows) | Container.Content(movies) | Container.Content(artists)]">Conditional</animation>
        <itemlayout width="495" height="450" condition="![[Skin.HasSetting(landscapeclearart) | Skin.HasSetting(landscapelogo) | Skin.HasSetting(landscapeonelogo)] + [Container.Content(tvshows) | Container.Content(movies) | Container.Content(artists)]] | [Container.Content(artists) + !Skin.HasSetting(landscapeonelogo)]">
            <include>LandscapeThumbs</include>
        </itemlayout>
        <focusedlayout width="600" height="450" condition="![[Skin.HasSetting(landscapeclearart) | Skin.HasSetting(landscapelogo) | Skin.HasSetting(landscapeonelogo)] + [Container.Content(tvshows) | Container.Content(movies) | Container.Content(artists)]] | [Container.Content(artists) + !Skin.HasSetting(landscapeonelogo)]">
            <control type="group">
                <animation effect="zoom" center="auto" start="100" end="122" time="300" tween="quadratic" reversible="false">Focus</animation>
                <animation type="UnFocus" condition="Control.HasFocus(503)">
                    <effect type="slide" end="-57" time="0" tween="quadratic" />
                    <effect type="zoom" center="auto" start="122" end="100" time="300" tween="quadratic" />
                </animation>
                <posx>57</posx>
                <include>LandscapeThumbs</include>
            </control>
        </focusedlayout>
        <itemlayout width="495" height="450" condition="[Skin.HasSetting(landscapelogo) + [Container.Content(tvshows) | Container.Content(movies)]]">
            <include>LandscapeLogoLayout</include>
        </itemlayout>
        <focusedlayout width="495" height="450" condition="Skin.HasSetting(landscapelogo) + [Container.Content(tvshows) | Container.Content(movies)]">
            <control type="group">
                <animation effect="zoom" center="auto" start="100" end="122" time="600" tween="back" reversible="false">Focus</animation>
                <animation effect="zoom" center="auto" start="122" end="100" time="200" tween="back" reversible="false">UnFocus</animation>
                <include>LandscapeLogoLayout</include>
            </control>
        </focusedlayout>
        <itemlayout width="516" height="450" condition="Skin.HasSetting(landscapeonelogo) + [Container.Content(tvshows) | Container.Content(movies) | Container.Content(artists)]"></itemlayout>
        <focusedlayout width="516" height="450" condition="Skin.HasSetting(landscapeonelogo) + [Container.Content(tvshows) | Container.Content(movies) | Container.Content(artists)]"></focusedlayout>
        <itemlayout width="495" height="450" condition="[Skin.HasSetting(landscapeclearart) + [Container.Content(tvshows) | Container.Content(movies)]]">
            <include>LandscapeClearArtLayout</include>
        </itemlayout>
        <focusedlayout width="495" height="450" condition="[Skin.HasSetting(landscapeclearart) + [Container.Content(tvshows) | Container.Content(movies)]]">
            <control type="group">
                <animation effect="zoom" center="auto" start="100" end="122" time="600" tween="back" reversible="false">Focus</animation>
                <animation effect="zoom" center="auto" start="122" end="100" time="200" tween="back" reversible="false">UnFocus</animation>
                <include>LandscapeClearArtLayout</include>
            </control>
        </focusedlayout>
    </include>
    <include name="lsfixed">
        <control type="fixedlist" id="503">
            <include>contents503list</include>
        </control>
    </include>
    <include name="lswrap">
        <control type="wraplist" id="503">
            <include>contents503list</include>
        </control>
    </include>
    <include name="MediaListView3">
        <control type="group">
            <visible>Control.IsVisible(503)</visible>
            <animation effect="slide" tween="cubic" time="500" start="0,806" end="0,0">VisibleChange</animation>
            <include condition="!Skin.HasSetting(showcasewrap)">lsfixed</include>
            <include condition="Skin.HasSetting(showcasewrap)">lswrap</include>
            <control type="group">
                <include>Animation_WindowFade200</include>
                <control type="image" id="8822">
                    <posx>650</posx>
                    <posy>810</posy>
                    <width>635</width>
                    <height>245</height>
                    <fadetime>200</fadetime>
                    <include>Animation_OpenCloseZoom_New</include>
                    <texture background="true" fallback="empty.png">$VAR[TVShowLogoVar]</texture>
                    <aspectratio>keep</aspectratio>
                    <animation effect="fade" delay="300" time="300" reversible="false">Hidden</animation>
                    <animation effect="fade" delay="200" end="100" time="300" condition="!Stringcompare(Control.GetLabel(8822),empty.png)">Conditional</animation>
                    <visible>Control.IsVisible(503) + Skin.HasSetting(landscapeonelogo) + [Container.Content(tvshows) | Container.Content(movies) | Container.Content(artists)]</visible>
                    <visible>![Container.OnNext | Container.OnPrevious]</visible>
                </control>
                <control type="label">
                    <animation effect="slide" end="0,-20" time="300" condition="Control.IsVisible(4050) | Control.HasFocus(61)">Conditional</animation>
                    <posx>510</posx>
                    <posy>1040</posy>
                    <width>900</width>
                    <align>center</align>
                    <include>Animation_VisibleChange200</include>
                    <font>Font_ShowcaseMainLabel2_Caps</font>
                    <scroll>true</scroll>
                    <scrollspeed>30</scrollspeed>
                    <textcolor>floor</textcolor>
                    <shadowcolor>floorshadow</shadowcolor>
                    <label>$INFO[ListItem.Label]</label>
                    <visible>![[Skin.HasSetting(landscapelogo) | Skin.HasSetting(landscapeonelogo)] + [Container.Content(tvshows) | Container.Content(movies) | Container.Content(artists)]]</visible>
                    <visible>!Container.Content(episodes)</visible>
                </control>
                <control type="label">
                    <animation effect="slide" end="0,-20" time="300" condition="Control.IsVisible(4050) | Control.HasFocus(61)">Conditional</animation>
                    <posx>510</posx>
                    <posy>1040</posy>
                    <width>900</width>
                    <align>center</align>
                    <include>Animation_VisibleChange200</include>
                    <font>Font_ShowcaseMainLabel2_Caps</font>
                    <scroll>true</scroll>
                    <scrollspeed>30</scrollspeed>
                    <textcolor>floor</textcolor>
                    <shadowcolor>floorshadow</shadowcolor>
                    <label>$INFO[ListItem.Title]</label>
                    <visible>Container.Content(episodes)</visible>
                    <visible>![[Skin.HasSetting(landscapelogo) | Skin.HasSetting(landscapeonelogo)] + [Container.Content(tvshows) | Container.Content(movies)]]</visible>
                </control>
                <control type="image">
                    <posy>-130</posy>
                    <width>1920</width>
                    <height>220</height>
                    <texture>views/logo_tagline_gradient.png</texture>
                    <colordiffuse>ffffffff</colordiffuse>
                    <visible>![Container.Content(movies) + IsEmpty(ListItem.TagLine)]</visible>
                    <visible>Skin.HasSetting(landscapeonelogo) + [Container.Content(tvshows) | Container.Content(movies)]</visible>
                    <include>Animation_VisibleChange200</include>
                </control>
                <control type="label">
                    <posx>510</posx>
                    <posy>1030</posy>
                    <width>900</width>
                    <align>center</align>
                    <include>Animation_VisibleChange200</include>
                    <font>Font_Bold20</font>
                    <scroll>true</scroll>
                    <scrollspeed>30</scrollspeed>
                    <shadowcolor>black</shadowcolor>
                    <label>$VAR[LandscapeLogoLabelVar]</label>
                    <visible>Skin.HasSetting(landscapelogo) + [Container.Content(tvshows) | Container.Content(movies)]  + !Control.HasFocus(61)</visible>
                </control>
                <control type="label">
                    <width>1920</width>
                    <aligny>bottom</aligny>
                    <align>center</align>
                    <include>Animation_VisibleChange200</include>
                    <scroll>true</scroll>
                    <scrollspeed>30</scrollspeed>
                    <font>Font_Bold19</font>
                    <shadowcolor>black</shadowcolor>
                    <label>$VAR[LandscapeLogoLabelVar]</label>
                    <visible>Skin.HasSetting(landscapeonelogo) + [Container.Content(tvshows) | Container.Content(movies)]  + !Control.HasFocus(61)</visible>
                </control>
                <control type="image">
                    <posx>200r</posx>
                    <posy>0</posy>
                    <width>200</width>
                    <height>200</height>
                    <visible>[Skin.HasSetting(landscapeclearart) | Skin.HasSetting(landscapelogo) | Skin.HasSetting(landscapeonelogo)]</visible>
                    <visible>[Skin.HasSetting(watchedoverlay) + SubString(ListItem(0).Overlay,OverlayWatched.png)] | [Skin.HasSetting(newstatus) + SubString(ListItem(0).Overlay,OverlayUnWatched.png) + [[Container.Content(movies) + [StringCompare(Window(Home).Property(LatestMovie.1.Title),ListItem(0).Label) | StringCompare(Window(Home).Property(LatestMovie.2.Title),ListItem(0).Label) | StringCompare(Window(Home).Property(LatestMovie.3.Title),ListItem(0).Label) | StringCompare(Window(Home).Property(LatestMovie.4.Title),ListItem(0).Label) | StringCompare(Window(Home).Property(LatestMovie.5.Title),ListItem(0).Label) | StringCompare(Window(Home).Property(LatestMovie.6.Title),ListItem(0).Label) | StringCompare(Window(Home).Property(LatestMovie.7.Title),ListItem(0).Label) | StringCompare(Window(Home).Property(LatestMovie.8.Title),ListItem(0).Label) | StringCompare(Window(Home).Property(LatestMovie.9.Title),ListItem(0).Label) | StringCompare(Window(Home).Property(LatestMovie.10.Title),ListItem(0).Label)]] | [[Container.Content(tvshows) | Container.Content(seasons)] + [StringCompare(Window(Home).Property(LatestEpisode.1.ShowTitle),ListItem(0).TvShowTitle) | StringCompare(Window(Home).Property(LatestEpisode.2.ShowTitle),ListItem(0).TvShowTitle) | StringCompare(Window(Home).Property(LatestEpisode.3.ShowTitle),ListItem(0).TvShowTitle) | StringCompare(Window(Home).Property(LatestEpisode.4.ShowTitle),ListItem(0).TvShowTitle) | StringCompare(Window(Home).Property(LatestEpisode.5.ShowTitle),ListItem(0).TvShowTitle) | StringCompare(Window(Home).Property(LatestEpisode.6.ShowTitle),ListItem(0).TvShowTitle) | StringCompare(Window(Home).Property(LatestEpisode.7.ShowTitle),ListItem(0).TvShowTitle) | StringCompare(Window(Home).Property(LatestEpisode.8.ShowTitle),ListItem(0).TvShowTitle) | StringCompare(Window(Home).Property(LatestEpisode.9.ShowTitle),ListItem(0).TvShowTitle) | StringCompare(Window(Home).Property(LatestEpisode.10.ShowTitle),ListItem(0).TvShowTitle)]] | [Container.Content(episodes) + [StringCompare(Window(Home).Property(LatestEpisode.1.EpisodeTitle),ListItem(0).Title) | StringCompare(Window(Home).Property(LatestEpisode.2.EpisodeTitle),ListItem(0).Title) | StringCompare(Window(Home).Property(LatestEpisode.3.EpisodeTitle),ListItem(0).Title) | StringCompare(Window(Home).Property(LatestEpisode.4.EpisodeTitle),ListItem(0).Title) | StringCompare(Window(Home).Property(LatestEpisode.5.EpisodeTitle),ListItem(0).Title) | StringCompare(Window(Home).Property(LatestEpisode.6.EpisodeTitle),ListItem(0).Title) | StringCompare(Window(Home).Property(LatestEpisode.7.EpisodeTitle),ListItem(0).Title) | StringCompare(Window(Home).Property(LatestEpisode.8.EpisodeTitle),ListItem(0).Title) | StringCompare(Window(Home).Property(LatestEpisode.9.EpisodeTitle),ListItem(0).Title) | StringCompare(Window(Home).Property(LatestEpisode.10.EpisodeTitle),ListItem(0).Title)]]]]</visible>
                    <include>Animation_VisibleChange200</include>
                    <texture>$INFO[ListItem.Overlay,thumbs/]</texture>
                </control>
            </control>
        </control>
    </include>
    <include name="LandscapeLogoLayout">
        <control type="image">
            <posx>52</posx>
            <posy>178</posy>
            <width>390</width>
            <height>164</height>
            <aspectratio aligny="bottom">keep</aspectratio>
            <texture background="true">$INFO[ListItem.Art(clearlogo)]</texture>
        </control>
        <control type="image">
            <posx>52</posx>
            <posy>345</posy>
            <width>390</width>
            <height>164</height>
            <aspectratio aligny="top">keep</aspectratio>
            <texture background="true" flipy="true">$INFO[ListItem.Art(clearlogo)]</texture>
            <animation effect="fade" start="10" end="10" time="200" tween="cubic" easing="inout" condition="true">Conditional</animation>
        </control>
        <control type="group">
            <visible>IsEmpty(ListItem.Art(clearlogo))</visible>
            <control type="label">
                <posx>248</posx>
                <posy>330</posy>
                <width>470</width>
                <align>center</align>
                <font>Font_Info_Caps</font>
                <textcolor>white2</textcolor>
                <shadowcolor>floorshadow</shadowcolor>
                <label>$VAR[SecondLabelVar]</label>
            </control>
            <control type="label">
                <posx>248</posx>
                <posy>296</posy>
                <width>470</width>
                <align>center</align>
                <font>Font_MainClassic4</font>
                <scroll>true</scroll>
                <scrollspeed>30</scrollspeed>
                <textcolor>white2</textcolor>
                <shadowcolor>floorshadow</shadowcolor>
                <label>$VAR[FirstLabelVar]</label>
            </control>
        </control>
    </include>
    <include name="LandscapeClearArtLayout">
        <control type="image">
            <posx>38</posx>
            <posy>-82</posy>
            <width>450</width>
            <height>400</height>
            <aspectratio aligny="bottom">keep</aspectratio>
            <texture background="true">$VAR[TVShowClearArtVar]</texture>
        </control>
        <control type="image">
            <posx>38</posx>
            <posy>295</posy>
            <width>450</width>
            <height>400</height>
            <aspectratio aligny="top">keep</aspectratio>
            <texture background="true" flipy="true">$VAR[TVShowClearArtVar]</texture>
            <animation effect="fade" start="10" end="10" time="200" tween="cubic" easing="inout" condition="true">Conditional</animation>
        </control>
        <control type="group">
            <visible>IsEmpty(ListItem.Art(clearlogo)) + IsEmpty(ListItem.Art(clearart))</visible>
            <control type="label">
                <posx>248</posx>
                <posy>330</posy>
                <width>470</width>
                <align>center</align>
                <font>Font_Info_Caps</font>
                <textcolor>white2</textcolor>
                <shadowcolor>floorshadow</shadowcolor>
                <label>$VAR[SecondLabelVar]</label>
            </control>
            <control type="label">
                <posx>248</posx>
                <posy>296</posy>
                <width>470</width>
                <align>center</align>
                <font>Font_MainClassic4</font>
                <scroll>true</scroll>
                <scrollspeed>30</scrollspeed>
                <textcolor>white2</textcolor>
                <shadowcolor>floorshadow</shadowcolor>
                <label>$VAR[FirstLabelVar]</label>
            </control>
        </control>
    </include>
</includes>